rest_framework_smoke/tests/__init__.py
rest_framework_smoke/tests/checklists.py
rest_framework_smoke/tests/mixins.py
rest_framework_smoke/tests/schemas.py
rest_framework_smoke-0.9.0.dist-info/LICENSE
rest_framework_smoke-0.9.0.dist-info/METADATA
rest_framework_smoke-0.9.0.dist-info/WHEEL
rest_framework_smoke-0.9.0.dist-info/top_level.txt
rest_framework_smoke-0.9.0.dist-info/RECORD
