Metadata-Version: 2.1
Name: rest-framework-smoke
Version: 0.9.0
Summary: Smoke tests for API built with Django Rest Framework
Home-page: https://github.com/just-work/rest-framework-smoke
Author: Sergey Tikhonov
Author-email: zimbler@gmail.com
License: MIT
Classifier: Development Status :: 4 - Beta
Classifier: Environment :: Console
Classifier: Framework :: Django :: 2.2
Classifier: Framework :: Django :: 3.0
Classifier: Framework :: Django :: 3.1
Classifier: Framework :: Django :: 3.2
Classifier: Framework :: Django :: 4.0
Classifier: Framework :: Django :: 4.1
Classifier: Operating System :: POSIX
Classifier: Programming Language :: Python :: 3.7
Classifier: Programming Language :: Python :: 3.8
Classifier: Programming Language :: Python :: 3.9
Classifier: Programming Language :: Python :: 3.10
Classifier: Topic :: Software Development :: Testing
License-File: LICENSE
Requires-Dist: Django
Requires-Dist: djangorestframework
Requires-Dist: jsonschema
